coinfection/__init__.py
coinfection/coinfection_detecting_algorithm.py
coinfection-0.0.1.dist-info/METADATA
coinfection-0.0.1.dist-info/WHEEL
coinfection-0.0.1.dist-info/licenses/LICENSE
coinfection-0.0.1.dist-info/RECORD
