Metadata-Version: 2.4
Name: coinfection
Version: 0.0.1
Summary: A novel algorithm to find multiple infection events in your CRISPR data.
Author-email: Marton Szamecz <szamecz.marci@gmail.com>
License-Expression: MIT
License-File: LICENSE
Classifier: Operating System :: OS Independent
Classifier: Programming Language :: Python :: 3
Requires-Python: >=3.9
Requires-Dist: matplotlib
Requires-Dist: numpy
Requires-Dist: pandas
Requires-Dist: seaborn
